<?xml version="1.0" encoding="utf-8"?>
<!DOCTYPE documentInfo>
<documentInfo url="/media/yoo/shared/precision_m6800.pdf">
 <generalInfo>
  <history>
   <oldPage viewport="76;C2:0.499425:-0.00533333:1"/>
   <oldPage viewport="75;C2:0.499425:0.0453333:1"/>
   <oldPage viewport="74;C2:0.499425:1.00267:1"/>
   <oldPage viewport="75;C2:0.499425:0.952:1"/>
   <oldPage viewport="76;C2:0.499425:0.314667:1"/>
   <oldPage viewport="59;C2:0.698968:0.489352:1"/>
   <oldPage viewport="76;C2:0.182913:0.497782:1"/>
   <oldPage viewport="59;C2:0.698968:0.489352:1"/>
   <oldPage viewport="76;C2:0.182913:0.497782:1"/>
   <oldPage viewport="59;C2:0.698968:0.489352:1"/>
   <current viewport="76;C2:0.499679:0.497516:1"/>
  </history>
  <views>
   <view name="PageView">
    <zoom mode="1" value="1.68178"/>
   </view>
  </views>
 </generalInfo>
</documentInfo>
